od.py
test_od.py
od-2.0.2.dist-info/LICENSE.txt
od-2.0.2.dist-info/METADATA
od-2.0.2.dist-info/WHEEL
od-2.0.2.dist-info/top_level.txt
od-2.0.2.dist-info/RECORD
