Metadata-Version: 2.1
Name: od
Version: 2.0.2
Summary: Shorthand syntax for building OrderedDicts
Home-page: https://github.com/epsy/od
Author: Yann Kaiser
Author-email: kaiser.yann@gmail.com
License: MIT
Keywords: OrderedDict,od,syntactic sugar
Platform: UNKNOWN
Classifier: Programming Language :: Python :: 3.5
Classifier: Programming Language :: Python :: 3.6
Classifier: Programming Language :: Python :: 3.7
Classifier: Programming Language :: Python :: 3.8
Classifier: Programming Language :: Python :: 3.9
Classifier: Programming Language :: Python :: 3.10
Classifier: Programming Language :: Python :: Implementation :: CPython
Classifier: Programming Language :: Python :: Implementation :: PyPy
Requires-Python: >=3.5
Provides-Extra: test
